{
  "classes": {
    "acrobat": {
      "id": "acrobat",
      "name": "Acrobat",
      "armorTier": "light",
      "coreStats": ["dex", "spd", "cha"],
      "guaranteedLevelUp": { "dex": 1, "spd": 1, "cha": 1 },
      "resources": ["stamina", "combo_points"],
      "primaryResource": "stamina",
      "skills": ["acrobatics", "subtlety", "daggers", "unarmed", "bows", "crossbows", "thrown", "lockpicking", "performing"],
      "startingBaseline": { "str": 10, "dex": 15, "con": 10, "int": 8, "spi": 8, "wis": 9, "spd": 15, "cha": 13 },
      "description": "A fast and evasive fighter who blends acrobatics with weapons."
    },
    "archer": {
      "id": "archer",
      "name": "Archer",
      "armorTier": "medium",
      "coreStats": ["dex"],
      "guaranteedLevelUp": { "dex": 2 },
      "resources": ["stamina", "combo_points"],
      "primaryResource": "stamina",
      "skills": ["bows", "crossbows", "marksmanship", "daggers", "one_handed_swords", "two_handed_swords", "fletching"],
      "startingBaseline": { "str": 10, "dex": 15, "con": 12, "int": 9, "spi": 10, "wis": 13, "spd": 14, "cha": 9 },
      "description": "A dex-driven ranged fighter who blends marksmanship with tracking and survival skills."
    },
    "armsman": {
      "id": "armsman",
      "name": "Armsman",
      "armorTier": "heavy",
      "coreStats": ["dex", "con", "wis"],
      "guaranteedLevelUp": { "dex": 1, "con": 1, "wis": 1 },
      "resources": ["stamina", "combo_points"],
      "primaryResource": "stamina",
      "skills": [
        "weaponsmithing", "engineering", "dueling",
        "one_handed_swords", "two_handed_swords",
        "one_handed_axes", "two_handed_axes",
        "one_handed_maces", "two_handed_maces",
        "daggers", "polearms", "guns", "bows", "crossbows", "thrown"
      ],
      "startingBaseline": { "str": 13, "dex": 15, "con": 15, "int": 8, "spi": 9, "wis": 13, "spd": 10, "cha": 9 },
      "description": "A master of weapons and heavy armor, durable and dex-driven."
    },
    "assassin": {
      "id": "assassin",
      "name": "Assassin",
      "armorTier": "light",
      "coreStats": ["dex", "spd"],
      "guaranteedLevelUp": { "dex": 1, "spd": 1 },
      "resources": ["stamina", "combo_points"],
      "primaryResource": "stamina",
      "skills": ["subtlety", "poisons", "daggers", "manipulation", "lockpicking", "alchemy", "guns", "thrown"],
      "startingBaseline": { "str": 10, "dex": 16, "con": 10, "int": 8, "spi": 10, "wis": 9, "spd": 16, "cha": 9 },
      "description": "A fast, evasive killer who manipulates and poisons."
    },
    "barbarian": {
      "id": "barbarian",
      "name": "Barbarian",
      "armorTier": "medium",
      "coreStats": ["str", "spi"],
      "guaranteedLevelUp": { "str": 2, "spi": 1 },
      "resources": ["stamina", "rage"],
      "primaryResource": "stamina",
      "skills": ["one_handed_axes", "two_handed_axes", "one_handed_maces", "two_handed_maces", "polearms", "unarmed", "mining", "herbalism", "fishing", "berserking"],
      "startingBaseline": { "str": 17, "dex": 10, "con": 12, "int": 8, "spi": 15, "wis": 9, "spd": 10, "cha": 8 },
      "description": "A durable and strong fighter who blends axes and maces with rage."
    },
    "bard": {
      "id": "bard",
      "name": "Bard",
      "armorTier": "light",
      "coreStats": ["dex", "cha", "int"],
      "guaranteedLevelUp": { "dex": 1, "cha": 2, "int": 1 },
      "resources": ["stamina", "mana"],
      "primaryResource": "stamina",
      "skills": ["performing", "daggers", "subtlety", "manipulation", "lockpicking", "morale", "dueling", "one_handed_swords", "bows", "crossbows", "restoration", "pyromancy", "cryomancy", "geomancy", "energetics"],
      "startingBaseline": { "str": 10, "dex": 14, "con": 10, "int": 9, "spi": 10, "wis": 9, "spd": 14, "cha": 15 },
      "description": "A dex-driven performer who blends music and magic with subtlety and manipulation."
    },
    "battlemage": {
      "id": "battlemage",
      "name": "Battlemage",
      "armorTier": "light",
      "coreStats": ["str", "int", "wis"],
      "guaranteedLevelUp": { "str": 1, "int": 1, "wis": 1 },
      "resources": ["stamina", "mana"],
      "primaryResource": "stamina",
      "skills": ["one_handed_swords", "two_handed_swords", "one_handed_axes", "two_handed_axes", "one_handed_maces", 
      "two_handed_maces", "dueling", "restoration", "manipulation", "pyromancy", "cryomancy", "geomancy", 
      "energetics", "divination"],
      "startingBaseline": { "str": 14, "dex": 10, "con": 12, "int": 14, "spi": 13, "wis": 10, "spd": 10, "cha": 9 },
      "description": "A durable and strong fighter who blends weapons with elemental magic."
    },
    "burglar": {
      "id": "burglar",
      "name": "Burglar",
      "armorTier": "light",
      "coreStats": ["dex", "cha"],
      "guaranteedLevelUp": { "dex": 1, "cha": 1 },
      "resources": ["stamina", "combo_points"],
      "primaryResource": "stamina",
      "skills": ["subtlety", "lockpicking", "daggers", "manipulation"],
      "startingBaseline": { "str": 10, "dex": 15, "con": 10, "int": 9, "spi": 9, "wis": 10, "spd": 14, "cha": 14 },
      "description": "A dex-driven thief who blends subtlety and manipulation with daggers."
    },
    "cleric": {
      "id": "cleric",
      "name": "Cleric",
      "armorTier": "medium",
      "coreStats": ["wis", "spi"],
      "guaranteedLevelUp": { "wis": 2, "spi": 1 },
      "resources": ["mana"],
      "primaryResource": "mana",
      "skills": ["restoration", "divination", "spiritcalling", "enchanting", "herbalism", "alchemy", "staves", 
      "wands", "one_handed_maces", "two_handed_maces", "shields"],
      "startingBaseline": { "str": 10, "dex": 9, "con": 11, "int": 10, "spi": 14, "wis": 17, "spd": 10, "cha": 10 },
      "description": "A durable caster who heals and protects through restoration and divination."
    },
    "dark_knight": {
      "id": "dark_knight",
      "name": "Dark Knight",
      "armorTier": "heavy",
      "coreStats": ["str", "con", "cha"],
      "guaranteedLevelUp": { "str": 1, "con": 1, "cha": 1 },
      "resources": ["stamina", "combo_points"],
      "primaryResource": "stamina",
      "skills": ["one_handed_swords", "two_handed_swords", "one_handed_maces", "two_handed_maces", 
      "shields", "dueling", "entropy", "necromancy", "protection", "cryomancy", "enchanting"],
      "startingBaseline": { "str": 15, "dex": 10, "con": 15, "int": 8, "spi": 10, "wis": 12, "spd": 10, "cha": 9 },
      "description": "A durable and strong fighter who blends weapons with darkness."
    },
    "dark_lord": {
      "id": "dark_lord",
      "name": "Dark Lord",
      "armorTier": "heavy",
      "coreStats": ["str", "con", "cha"],
      "guaranteedLevelUp": { "str": 1, "con": 1, "cha": 1 },
      "resources": ["stamina", "combo_points"],
      "primaryResource": "stamina",
      "skills": ["one_handed_swords", "two_handed_swords", "one_handed_maces", "two_handed_maces", 
      "shields", "dueling", "entropy", "necromancy", "protection", "cryomancy", "enchanting", "morale", "manipulation", "ettiquette"],
      "startingBaseline": { "str": 15, "dex": 10, "con": 15, "int": 8, "spi": 10, "wis": 12, "spd": 10, "cha": 9 },
      "description": "A durable and strong fighter who blends weapons with darkness."
    },
    "death_knight": {
      "id": "death_knight",
      "name": "Death Knight",
      "armorTier": "heavy",
      "coreStats": ["str", "con", "cha"],
      "guaranteedLevelUp": { "str": 1, "con": 1, "cha": 1 },
      "resources": ["stamina", "combo_points"],
      "primaryResource": "stamina",
      "skills": ["one_handed_swords", "two_handed_swords", "one_handed_maces", "two_handed_maces", 
      "one_handed_axes", "two_handed_axes", "berserking", "entropy", "necromancy", "sangromancy", 
      "spiritcalling", "protection", "cryomancy", "enchanting", "madness"],
      "startingBaseline": { "str": 15, "dex": 10, "con": 15, "int": 8, "spi": 10, "wis": 12, "spd": 10, "cha": 9 },
      "description": "A durable and strong fighter who blends weapons with death."
    },
    "druid": {
      "id": "druid",
      "name": "Druid",
      "armorTier": "light",
      "coreStats": ["wis", "spi"],
      "guaranteedLevelUp": { "wis": 1, "spi": 2 },
      "resources": ["mana"],
      "primaryResource": "mana",
      "skills": ["restoration", "divination", "spiritcalling", "shapeshifting", "astromancy", "geomancy", 
      "hydromancy", "biomancy", "herbalism", "skinning", "leatherworking", "one_handed_maces", "two_handed_maces", 
      "staves"],
      "startingBaseline": { "str": 10, "dex": 9, "con": 11, "int": 10, "spi": 14, "wis": 17, "spd": 10, "cha": 10 },
      "description": "A durable caster who heals and protects through restoration and divination."
    },
    "elementalist": {
      "id": "elementalist",
      "name": "Elementalist",
      "armorTier": "light",
      "coreStats": ["int", "spi"],
      "guaranteedLevelUp": { "int": 2, "spi": 1 },
      "resources": ["mana"],
      "primaryResource": "mana",
      "skills": ["pyromancy", "cryomancy", "geomancy", "energetics", "hydromancy", "enchanting", "staves", "wands"],
      "startingBaseline": { "str": 8, "dex": 9, "con": 9, "int": 17, "spi": 14, "wis": 11, "spd": 10, "cha": 10 },
      "description": "A pure elementalist channeling the schools through mana."
    },
    "healer": {
      "id": "healer",
      "name": "Healer",
      "armorTier": "clothing",
      "coreStats": ["int", "wis"],
      "guaranteedLevelUp": { "int": 1, "wis": 1 },
      "resources": ["mana"],
      "primaryResource": "mana",
      "skills": ["restoration", "divination", "spiritcalling","enchanting", "herbalism", "alchemy", "staves", "wands"],
      "startingBaseline": { "str": 8, "dex": 9, "con": 10, "int": 16, "spi": 12, "wis": 15, "spd": 10, "cha": 10 },
      "description": "A clothing caster who heals and protects through restoration and divination."
    },
    "illusionist": {
      "id": "illusionist",
      "name": "Illusionist",
      "armorTier": "clothing",
      "coreStats": ["int", "cha"],
      "guaranteedLevelUp": { "int": 1, "cha": 1 },
      "resources": ["mana"],
      "primaryResource": "mana",
      "skills": ["staves", "wands", "daggers", "manipulation", "madness", "morale", "enchanting", "alchemy", "divination"],
      "startingBaseline": { "str": 8, "dex": 10, "con": 9, "int": 16, "spi": 12, "wis": 10, "spd": 11, "cha": 15 },
      "description": "A clothing caster who bends minds through manipulation and madness."
    },
    "knight": {
      "id": "knight",
      "name": "Knight",
      "armorTier": "heavy",
      "coreStats": ["str", "con", "cha"],
      "guaranteedLevelUp": { "str": 1, "con": 1, "cha": 1 },
      "resources": ["stamina", "combo_points"],
      "primaryResource": "stamina",
      "skills": ["one_handed_swords", "two_handed_swords", "one_handed_maces", "two_handed_maces", "polearms", "shields", "dueling", "bows", "academics"],
      "startingBaseline": { "str": 15, "dex": 10, "con": 15, "int": 8, "spi": 10, "wis": 12, "spd": 10, "cha": 9 },
      "description": "A durable and strong fighter who blends weapons with restoration."
    },
    "lord": {
      "id": "lord",
      "name": "Lord",
      "armorTier": "heavy",
      "coreStats": ["str", "con", "cha"],
      "guaranteedLevelUp": { "str": 1, "con": 1, "cha": 1 },
      "resources": ["stamina", "combo_points"],
      "primaryResource": "stamina",
      "skills": ["one_handed_swords", "two_handed_swords", "one_handed_maces", "two_handed_maces", 
      "polearms", "shields", "dueling", "morale", "bows", "protection"],
      "startingBaseline": { "str": 15, "dex": 10, "con": 15, "int": 8, "spi": 10, "wis": 12, "spd": 10, "cha": 9 },
      "description": "A durable and strong fighter who blends weapons with restoration."
    },
    "mage": {
      "id": "mage",
      "name": "Mage",
      "armorTier": "clothing",
      "coreStats": ["int"],
      "guaranteedLevelUp": { "int": 3 },
      "resources": ["mana"],
      "primaryResource": "mana",
      "skills": ["pyromancy", "cryomancy", "geomancy", "energetics", "hydromancy", "astromancy","academics", "enchanting", "staves", "wands"],
      "startingBaseline": { "str": 8, "dex": 9, "con": 9, "int": 17, "spi": 14, "wis": 11, "spd": 10, "cha": 10 },
      "description": "A pure mage channeling the schools through mana."
    },
    "miner": {
      "id": "miner",
      "name": "Miner",
      "armorTier": "medium",
      "coreStats": ["con", "spi"],
      "guaranteedLevelUp": { "con": 1, "spi": 1 },
      "resources": ["stamina"],
      "primaryResource": "stamina",
      "skills": ["mining", "fabrication", "metallurgy", "two_handed_axes", "two_handed_maces"],
      "startingBaseline": { "str": 14, "dex": 10, "con": 15, "int": 9, "spi": 12, "wis": 11, "spd": 10, "cha": 8 },
      "description": "A durable craftsman and miner who wields maces and polearms."
    },
    "monk": {
      "id": "monk",
      "name": "Monk",
      "armorTier": "clothing",
      "coreStats": ["str", "dex", "wis"],
      "guaranteedLevelUp": { "str": 1, "dex": 1, "wis": 1 },
      "resources": ["stamina", "combo_points"],
      "primaryResource": "stamina",
      "skills": ["unarmed", "acrobatics", "restoration", "spiritcalling", "divination"],
      "startingBaseline": { "str": 14, "dex": 14, "con": 12, "int": 9, "spi": 10, "wis": 13, "spd": 14, "cha": 9 },
      "description": "A durable and dex-driven fighter who blends martial arts with restoration."
    },
    "nightblade": {
      "id": "nightblade",
      "name": "Nightblade",
      "armorTier": "light",
      "coreStats": ["dex", "int"],
      "guaranteedLevelUp": { "dex": 1, "int": 1 },
      "resources": ["stamina", "mana", "combo_points"],
      "primaryResource": "stamina",
      "skills": ["subtlety", "poisons", "daggers", "manipulation", "lockpicking", "madness", "energetics", "pyromancy", "cryomancy"],
      "startingBaseline": { "str": 10, "dex": 16, "con": 10, "int": 9, "spi": 10, "wis": 9, "spd": 16, "cha": 14 },
      "description": "A dex-driven manipulator who blends subtlety and poisons with daggers."
    },
    "paladin": {
      "id": "paladin",
      "name": "Paladin",
      "armorTier": "heavy",
      "coreStats": ["str", "wis", "cha"],
      "guaranteedLevelUp": { "str": 1, "wis": 1, "cha": 1 },
      "resources": ["stamina", "mana"],
      "primaryResource": "stamina",
      "skills": ["one_handed_swords", "two_handed_swords", "one_handed_maces", "two_handed_maces", "justice", 
      "polearms", "shields", "restoration", "divination", "spiritcalling", "protection", "first_aid", "dueling", 
      "morale"],
      "startingBaseline": { "str": 15, "dex": 10, "con": 15, "int": 8, "spi": 10, "wis": 12, "spd": 10, "cha": 9 },
      "description": "A durable and strong fighter who blends weapons with restoration."
    },
    "pirate": {
      "id": "pirate",
      "name": "Pirate",
      "armorTier": "medium",
      "coreStats": ["dex", "str"],
      "guaranteedLevelUp": { "dex": 1, "str": 1 },
      "resources": ["stamina", "combo_points"],
      "primaryResource": "stamina",
      "skills": ["subtlety", "dueling", "berserking", "lockpicking", "daggers", "one_handed_swords",  "one_handed_maces", "one_handed_axes", "bows", "crossbows", "guns", "aeronautics", "fishing"],
      "startingBaseline": { "str": 12, "dex": 15, "con": 12, "int": 9, "spi": 10, "wis": 11, "spd": 14, "cha": 13 },
      "description": "A dex-driven manipulator who blends subtlety and daggers with swords and maces."
    },
    "ranger": {
      "id": "ranger",
      "name": "Ranger",
      "armorTier": "heavy",
      "coreStats": ["dex", "wis", "con"],
      "guaranteedLevelUp": { "dex": 1, "wis": 1, "con": 1 },
      "resources": ["stamina", "combo_points"],
      "primaryResource": "stamina",
      "skills": ["dueling", "bows", "crossbows", "one_handed_axes", "two_handed_axes", "first_aid", "guns", "marksmanship", "tracking", "herbalism", "fishing", "woodcutting", "one_handed_swords", "two_handed_swords"],
      "startingBaseline": { "str": 12, "dex": 15, "con": 12, "int": 9, "spi": 10, "wis": 13, "spd": 14, "cha": 9 },
      "description": "A dex-driven outdoorsman who blends marksmanship with tracking and survival skills."
    },
    "rogue": {
      "id": "rogue",
      "name": "Rogue",
      "armorTier": "medium",
      "coreStats": ["dex", "str", "cha"],
      "guaranteedLevelUp": { "dex": 1, "str": 1, "cha": 1 },
      "resources": ["stamina", "combo_points"],
      "primaryResource": "stamina",
      "skills": ["subtlety", "poisons", "daggers", "one_handed_axes", "one_handed_maces", "one_handed_swords", "dueling", "lockpicking"],
      "startingBaseline": { "str": 10, "dex": 16, "con": 10, "int": 9, "spi": 10, "wis": 9, "spd": 16, "cha": 14 },
      "description": "A dex-driven manipulator who blends subtlety and poisons with daggers."
    },
    "ragefiend": {
      "id": "ragefiend",
      "name": "Ragefiend",
      "armorTier": "light",
      "coreStats": ["str", "dex"],
      "guaranteedLevelUp": { "str": 1, "dex": 1 },
      "resources": ["rage", "combo_points"],
      "primaryResource": "rage",
      "skills": ["dueling", "daggers", "thrown", "guns", "berserking", "madness", "sangromancy", "spiritcalling"],
      "startingBaseline": { "str": 17, "dex": 10, "con": 15, "int": 8, "spi": 9, "wis": 12, "spd": 10, "cha": 9 },
      "description": "A durable and strong fighter who blends weapons with light armor."
    },
    "shaman": {
      "id": "shaman",
      "name": "Shaman",
      "armorTier": "medium",
      "coreStats": ["wis", "spi", "str"],
      "guaranteedLevelUp": { "wis": 1, "spi": 1, "str": 1 },
      "resources": ["mana", "rage"],
      "primaryResource": "mana",
      "skills": ["restoration", "divination", "spiritcalling", "enchanting", "herbalism", "alchemy", "berserking", 
      "staves", "one_handed_axes", "two_handed_axes", "one_handed_maces", "two_handed_maces", "energetics", 
      "pyromancy", "cryomancy", "geomancy", "hydromancy", "astromancy", "biomancy"],
      "startingBaseline": { "str": 10, "dex": 9, "con": 11, "int": 10, "spi": 14, "wis": 17, "spd": 10, "cha": 10 },
      "description": "A durable caster who heals and protects through restoration and divination."
    },
    "sorcerer": {
      "id": "sorcerer",
      "name": "Sorcerer",
      "armorTier": "medium",
      "coreStats": ["int", "wis"],
      "guaranteedLevelUp": { "int": 1, "wis": 2 },
      "resources": ["mana"],
      "primaryResource": "mana",
      "skills": ["pyromancy", "cryomancy", "geomancy", "energetics", "hydromancy", "astromancy", "necromancy", "enchanting", "staves", "daggers", "one_handed_maces", "two_handed_maces", "wands"],
      "startingBaseline": { "str": 8, "dex": 9, "con": 9, "int": 17, "spi": 14, "wis": 11, "spd": 10, "cha": 10 },
      "description": "A pure sorcerer channeling the schools through mana."
    },
    "spellsword": {
      "id": "spellsword",
      "name": "Spellsword",
      "armorTier": "medium",
      "coreStats": ["str", "int", "wis"],
      "guaranteedLevelUp": { "str": 1, "int": 1, "wis": 1 },
      "resources": ["stamina", "mana"],
      "primaryResource": "stamina",
      "skills": ["one_handed_swords", "two_handed_swords", "shields", "dueling", "pyromancy", "cryomancy", "geomancy", "energetics", "hydromancy", "astromancy", "divination"],
      "startingBaseline": { "str": 14, "dex": 10, "con": 12, "int": 14, "spi": 13, "wis": 10, "spd": 10, "cha": 9 },
      "description": "A durable and strong fighter who blends weapons with elemental magic."
    },
    "sun_knight": {
      "id": "sun_knight",
      "name": "Sun Knight",
      "armorTier": "heavy",
      "coreStats": ["str", "wis", "cha"],
      "guaranteedLevelUp": { "str": 1, "wis": 1, "cha": 1 },
      "resources": ["rage", "mana"],
      "primaryResource": "rage",
      "skills": ["one_handed_swords", "two_handed_swords", "one_handed_maces", "two_handed_maces", 
      "polearms", "shields", "berserking", "morale", "restoration", "divination", "spiritcalling", 
      "protection", "pyromancy", "artillery", "ettiquette"],
      "startingBaseline": { "str": 15, "dex": 10, "con": 15, "int": 8, "spi": 10, "wis": 12, "spd": 10, 
      "cha": 9 },
      "description": "A durable and strong fighter who blends weapons with restoration."
    },
    "survivalist": {
      "id": "survivalist",
      "name": "Survivalist",
      "armorTier": "medium",
      "coreStats": ["con", "spi", "spd"],
      "guaranteedLevelUp": { "con": 1, "spi": 1, "spd": 1 },
      "resources": ["stamina", "mana"],
      "primaryResource": "stamina",
      "skills": [
        "biomancy", "fishing", "mining", "herbalism", "woodcutting", "first_aid", "cooking",
        "polearms", "one_handed_axes", "two_handed_axes", "bows", "daggers"
      ],
      "startingBaseline": { "str": 12, "dex": 12, "con": 14, "int": 9, "spi": 13, "wis": 11, "spd": 13, "cha": 8 },
      "description": "A durable, mobile outdoorsman blending Biomancy with weapons and survival crafts."
    },
    "swordsman": {
      "id": "swordsman",
      "name": "Swordsman",
      "armorTier": "medium",
      "coreStats": ["dex", "str", "spd"],
      "guaranteedLevelUp": { "dex": 1, "str": 1, "spd": 1 },
      "resources": ["stamina", "combo_points"],
      "primaryResource": "stamina",
      "skills": [
        "one_handed_swords", "two_handed_swords", "dueling", "weaponsmithing", "shields", "marksmanship"
      ],
      "startingBaseline": { "str": 13, "dex": 15, "con": 11, "int": 8, "spi": 9, "wis": 12, "spd": 14, "cha": 10 },
      "description": "A dex-driven swordsman who blends swordplay with subtlety and traps."
    },
    "thief": {
      "id": "thief",
      "name": "Thief",
      "armorTier": "light",
      "coreStats": ["dex", "cha"],
      "guaranteedLevelUp": { "dex": 1, "cha": 1 },
      "resources": ["stamina", "combo_points"],
      "primaryResource": "stamina",
      "skills": ["subtlety", "poisons", "daggers", "manipulation", "lockpicking", "thrown"],
      "startingBaseline": { "str": 10, "dex": 16, "con": 10, "int": 9, "spi": 10, "wis": 9, "spd": 16, "cha": 14 },
      "description": "A dex-driven manipulator who blends subtlety and poisons with daggers."
    },
    "trickster": {
      "id": "trickster",
      "name": "Trickster",
      "armorTier": "light",
      "coreStats": ["spd", "dex"],
      "guaranteedLevelUp": { "spd": 1, "dex": 1 },
      "resources": ["combo_points", "stamina"],
      "primaryResource": "combo_points",
      "skills": ["dueling", "daggers", "thrown", "guns", "lockpicking", "subtlety"],
      "startingBaseline": { "str": 17, "dex": 10, "con": 15, "int": 8, "spi": 9, "wis": 12, "spd": 10, "cha": 9 },
      "description": "A durable and strong fighter who blends weapons with light armor."
    },
    "warlock": {
      "id": "warlock",
      "name": "Warlock",
      "armorTier": "clothing",
      "coreStats": ["int", "spi", "cha"],
      "guaranteedLevelUp": { "int": 1, "spi": 1, "cha": 1 },
      "resources": ["mana"],
      "primaryResource": "mana",
      "skills": ["necromancy", "pyromancy", "summoning", "entropy", "enchanting", "staves", "wands", 
      "manipulation", "madness"],
      "startingBaseline": { "str": 8, "dex": 9, "con": 9, "int": 17, "spi": 14, "wis": 11, "spd": 10, "cha": 10 },
      "description": "A pure warlock channeling the schools through mana."
    },
    "warrior": {
      "id": "warrior",
      "name": "Warrior",
      "armorTier": "heavy",
      "coreStats": ["str", "con"],
      "guaranteedLevelUp": { "str": 1, "con": 1 },
      "resources": ["rage", "combo_points"],
      "primaryResource": "rage",
      "skills": ["one_handed_swords", "two_handed_swords", "one_handed_axes", "two_handed_axes", 
      "one_handed_maces", "two_handed_maces", "polearms", "shields", "berserking", "protection", "bows", 
      "crossbows", "guns"],
      "startingBaseline": { "str": 17, "dex": 10, "con": 15, "int": 8, "spi": 9, "wis": 12, "spd": 10, "cha": 9 },
      "description": "A durable and strong fighter who blends weapons with heavy armor."
    }
  },
  "maxLevel": 99
}
