{
  "mobs": {

    "mheader0": "//////////////////////////////////////////////////////////////////////////////",
    "mheader1": "///// RATH MOBS /// RATH MOBS /// RATH MOBS /// RATH MOBS /// RATH MOBS //////",
    "mheader2": "//////////////////////////////////////////////////////////////////////////////",

    "------Colonial_Sewers------": "zone_colonial_sewers",

    "colonial_sewer_rat": {
      "id": "colonial_sewer_rat",
      "name": "Colonial Sewer Rat",
      "_version": 1,
      "type": "beast",
      "level": 1,
      "baseStats": { "str": 4, "dex": 6, "con": 5, "int": 1, "spi": 2, "wis": 2, "spd": 5, "cha": 1 },
      "abilities": ["basic_attack"],
      "aiProfile": "aggressive",
      "loot": [],
      "xpValue": 20,
      "currencyDrop": null,
      "tags": ["beast", "vermin", "zone_colonial_sewers"],
      "butcheryXp": 8,
      "butcheryLoot": [
        { "type": "meat", "itemId": "raw_rat_meat", "chance": 1.0, "minQty": 1, "maxQty": 2 },
        { "type": "hide", "itemId": "thin_hide",    "chance": 0.5, "qty": 1 },
        { "type": "bone", "itemId": "small_bone",   "chance": 0.6, "qty": 1 }
      ],
      "description": "A rat that has adapted to the sewers beneath Rath."
    },

    "tunnel_roach": {
      "id": "tunnel_roach",
      "name": "Tunnel Roach",
      "_version": 1,
      "type": "beast",
      "level": 1,
      "baseStats": { "str": 5, "dex": 6, "con": 8, "int": 1, "spi": 2, "wis": 2, "spd": 5, "cha": 1 },
      "abilities": ["basic_attack"],
      "aiProfile": "aggressive",
      "loot": [],
      "xpValue": 25,
      "currencyDrop": null,
      "tags": ["beast", "vermin", "zone_colonial_sewers"],
      "butcheryXp": 6,
      "butcheryLoot": [
        { "type": "meat", "itemId": "stringy_roach_meat", "chance": 1.0, "minQty": 1, "maxQty": 2 },
        { "type": "bone", "itemId": "small_bone",         "chance": 0.5, "qty": 1 }
      ],
      "description": "A bloated roach grown fat in the sewers beneath Rath."
    },

    "sewer_mutant": {
      "id": "sewer_mutant",
      "name": "Sewer Mutant",
      "_version": 1,
      "type": "aberration",
      "level": 3,
      "baseStats": { "str": 15, "dex": 8, "con": 22, "int": 3, "spi": 4, "wis": 4, "spd": 7, "cha": 1 },
      "abilities": ["basic_attack"],
      "aiProfile": "aggressive",
      "isBoss": true,
      "loot": [],
      "xpValue": 160,
      "currencyDrop": { "min": 40, "max": 90 },
      "tags": ["aberration", "boss", "zone_colonial_sewers", "arc_under_rath"],
      "butcheryXp": 20,
      "butcheryLoot": [
        { "type": "bone", "itemId": "small_bone", "chance": 0.8, "minQty": 1, "maxQty": 2 }
      ],
      "description": "A hulking thing the sewers made. Whatever it once was, hunger and mutation left only mass, teeth, and appetite — enough to tear through a slaver crew and everyone they were dragging."
    },

    "mheader3": "//////////////////////////////////////////////////////////////////////////////",
    "mheader4": "///// TEST MOBS /// TEST MOBS /// TEST MOBS /// TEST MOBS /// TEST MOBS //////",
    "mheader5": "//////////////////////////////////////////////////////////////////////////////",

    "enemy_test_grunt": {
      "id": "enemy_test_grunt",
      "name": "Test Grunt",
      "_version": 1,
      "type": "humanoid",
      "baseStats": { "str": 16, "agi": 14, "sta": 15, "int": 8, "spi": 9 },
      "abilities": ["ability_alpha"],
      "aiProfile": "aggressive",
      "loot": [
        { "itemId": "item_test_scrap", "chance": 0.5, "qty": 1 }
      ],
      "currencyDrop": null,
      "xpValue": 50,
      "tags": ["test"],
      "description": "A synthetic enemy for testing."
    },
    "enemy_test_caster": {
      "id": "enemy_test_caster",
      "name": "Test Caster",
      "_version": 1,
      "type": "humanoid",
      "baseStats": { "str": 10, "agi": 12, "sta": 12, "int": 20, "spi": 16 },
      "abilities": ["ability_beta"],
      "aiProfile": "aggressive",
      "loot": [],
      "currencyDrop": null,
      "xpValue": 65,
      "tags": ["test"],
      "description": "A synthetic caster enemy for testing."
    }
  }
}
